Infequevalence/inf_eqvln.py
Infequevalence-0.0.6.dist-info/Licence.txt
Infequevalence-0.0.6.dist-info/METADATA
Infequevalence-0.0.6.dist-info/WHEEL
Infequevalence-0.0.6.dist-info/top_level.txt
Infequevalence-0.0.6.dist-info/RECORD
