Metadata-Version: 2.1
Name: Infequevalence
Version: 0.0.6
Summary: Information Equivalence for Cubic regression Model
Home-page: UNKNOWN
Author: Developer Rohit
Author-email: 143rohitbehera@gmail.com
License: UNKNOWN
Keywords: python,Information Equevalence,DE LA GARZA PHENOMENON,EXACT DESIGNS,developerrohit
Platform: UNKNOWN
Classifier: Development Status :: 1 - Planning
Classifier: Intended Audience :: Developers
Classifier: Programming Language :: Python :: 3
Classifier: Operating System :: Unix
Classifier: Operating System :: MacOS :: MacOS X
Classifier: Operating System :: Microsoft :: Windows
License-File: Licence.txt
Requires-Dist: numpy
